[
  {
    "Index": "1",
    "SkillName": "NormalAttack",
    "SkillType": "0",
    "Grade": "1",
    "Description": "기본 공격",
    "SkillCoolTime": "0.8",
    "SkillBaseDamage": "3",
    "SkillCoefficient": "0.2",
    "SkillRange": "3",
    "AttackCount": "1",
    "ProjectileSpeed": "5"
  },
  {
    "Index": "2",
    "SkillName": "NormalAttack",
    "SkillType": "0",
    "Grade": "2",
    "Description": "기본 공격",
    "SkillCoolTime": "0.7",
    "SkillBaseDamage": "4",
    "SkillCoefficient": "0.3",
    "SkillRange": "3.5",
    "AttackCount": "1",
    "ProjectileSpeed": "6"
  },
  {
    "Index": "3",
    "SkillName": "NormalAttack",
    "SkillType": "0",
    "Grade": "3",
    "Description": "기본 공격",
    "SkillCoolTime": "0.6",
    "SkillBaseDamage": "5",
    "SkillCoefficient": "0.4",
    "SkillRange": "4",
    "AttackCount": "1",
    "ProjectileSpeed": "7"
  },
  {
    "Index": "4",
    "SkillName": "NormalAttack",
    "SkillType": "0",
    "Grade": "4",
    "Description": "기본 공격",
    "SkillCoolTime": "0.5",
    "SkillBaseDamage": "6",
    "SkillCoefficient": "0.4",
    "SkillRange": "4.5",
    "AttackCount": "1",
    "ProjectileSpeed": "7"
  },
  {
    "Index": "5",
    "SkillName": "Explosion",
    "SkillType": "0",
    "Grade": "1",
    "Description": "빠방 터진댜",
    "SkillCoolTime": "2",
    "SkillBaseDamage": "5",
    "SkillCoefficient": "0.2",
    "SkillRange": "5",
    "AttackCount": "3",
    "ProjectileSpeed": "-1"
  },
  {
    "Index": "6",
    "SkillName": "Explosion",
    "SkillType": "0",
    "Grade": "2",
    "Description": "빠바방 터진댜",
    "SkillCoolTime": "2",
    "SkillBaseDamage": "5",
    "SkillCoefficient": "0.2",
    "SkillRange": "5",
    "AttackCount": "5",
    "ProjectileSpeed": "-1"
  },
  {
    "Index": "7",
    "SkillName": "Explosion",
    "SkillType": "0",
    "Grade": "3",
    "Description": "빠바바방 터진댜",
    "SkillCoolTime": "2",
    "SkillBaseDamage": "6",
    "SkillCoefficient": "0.2",
    "SkillRange": "5",
    "AttackCount": "5",
    "ProjectileSpeed": "-1"
  },
  {
    "Index": "8",
    "SkillName": "Beam",
    "SkillType": "0",
    "Grade": "1",
    "Description": "하나만 조진다",
    "SkillCoolTime": "3",
    "SkillBaseDamage": "10",
    "SkillCoefficient": "1",
    "SkillRange": "3.5",
    "AttackCount": "1",
    "ProjectileSpeed": "-1"
  },
  {
    "Index": "9",
    "SkillName": "Beam",
    "SkillType": "0",
    "Grade": "2",
    "Description": "더 쎄게 조진다",
    "SkillCoolTime": "3",
    "SkillBaseDamage": "10",
    "SkillCoefficient": "1",
    "SkillRange": "4",
    "AttackCount": "1",
    "ProjectileSpeed": "-1"
  },
  {
    "Index": "10",
    "SkillName": "Beam",
    "SkillType": "0",
    "Grade": "3",
    "Description": "더더 쎼게 조진다아",
    "SkillCoolTime": "3",
    "SkillBaseDamage": "11",
    "SkillCoefficient": "1",
    "SkillRange": "4",
    "AttackCount": "1",
    "ProjectileSpeed": "-1"
  },
  {
    "Index": "11",
    "SkillName": "Bubble",
    "SkillType": "0",
    "Grade": "1",
    "Description": "방울방울",
    "SkillCoolTime": "5",
    "SkillBaseDamage": "8",
    "SkillCoefficient": "0.3",
    "SkillRange": "-1",
    "AttackCount": "1",
    "ProjectileSpeed": "-1"
  },
  {
    "Index": "12",
    "SkillName": "Bubble",
    "SkillType": "0",
    "Grade": "2",
    "Description": "예쁜 방울방울",
    "SkillCoolTime": "5",
    "SkillBaseDamage": "9",
    "SkillCoefficient": "0.3",
    "SkillRange": "-1",
    "AttackCount": "1",
    "ProjectileSpeed": "-1"
  },
  {
    "Index": "13",
    "SkillName": "Bubble",
    "SkillType": "0",
    "Grade": "3",
    "Description": "가장 센 방울방울",
    "SkillCoolTime": "5",
    "SkillBaseDamage": "10",
    "SkillCoefficient": "0.3",
    "SkillRange": "-1",
    "AttackCount": "1",
    "ProjectileSpeed": "-1"
  },
  {
    "Index": "14",
    "SkillName": "NormalAttackUp",
    "SkillType": "0",
    "Grade": "1",
    "Description": "기본 공격 쎄진당",
    "SkillCoolTime": "-1",
    "SkillBaseDamage": "-1",
    "SkillCoefficient": "-1",
    "SkillRange": "-1",
    "AttackCount": "-1",
    "ProjectileSpeed": "-1"
  },
  {
    "Index": "15",
    "SkillName": "NormalAttackUp",
    "SkillType": "0",
    "Grade": "2",
    "Description": "또 쎄진다",
    "SkillCoolTime": "-1",
    "SkillBaseDamage": "-1",
    "SkillCoefficient": "-1",
    "SkillRange": "-1",
    "AttackCount": "-1",
    "ProjectileSpeed": "-1"
  },
  {
    "Index": "16",
    "SkillName": "NormalAttackUp",
    "SkillType": "0",
    "Grade": "3",
    "Description": "또또 쎄진다",
    "SkillCoolTime": "-1",
    "SkillBaseDamage": "-1",
    "SkillCoefficient": "-1",
    "SkillRange": "-1",
    "AttackCount": "-1",
    "ProjectileSpeed": "-1"
  }
]